README.md
setup.py
mldb/__init__.py
mldb.egg-info/PKG-INFO
mldb.egg-info/SOURCES.txt
mldb.egg-info/dependency_links.txt
mldb.egg-info/entry_points.txt
mldb.egg-info/not-zip-safe
mldb.egg-info/requires.txt
mldb.egg-info/top_level.txt