Metadata-Version: 2.1
Name: mldb
Version: 0.0.1
Summary: ML DataBase
Home-page: https://github.com/ctuning/ck
Author: Grigori Fursin
Author-email: gfursin@gmail.com
License: Apache 2.0
Keywords: ck,database,reuse,api
Platform: UNKNOWN
Classifier: Development Status :: 1 - Planning
Classifier: License :: OSI Approved :: Apache Software License
Classifier: Programming Language :: Python
Classifier: Intended Audience :: Developers
